setup.py
dsnd_Probability_1/Binomialdistribution.py
dsnd_Probability_1/Gaussiandistribution.py
dsnd_Probability_1/Generaldistribution.py
dsnd_Probability_1/__init__.py
dsnd_Probability_1.egg-info/PKG-INFO
dsnd_Probability_1.egg-info/SOURCES.txt
dsnd_Probability_1.egg-info/dependency_links.txt
dsnd_Probability_1.egg-info/not-zip-safe
dsnd_Probability_1.egg-info/top_level.txt