Metadata-Version: 1.0
Name: dsnd-Probability-1
Version: 1.0
Summary: Gaussian distributions
Home-page: UNKNOWN
Author: Sumeet Gairola
Author-email: UNKNOWN
License: UNKNOWN
Platform: UNKNOWN
